lectern/__init__.py
lectern/__main__.py
lectern/cli.py
lectern/contrib/__init__.py
lectern/contrib/define.py
lectern/contrib/messaging.py
lectern/contrib/plugin.py
lectern/contrib/relative_location.py
lectern/contrib/require.py
lectern/contrib/script.py
lectern/contrib/tagged_function_shorthand.py
lectern/contrib/vanilla.py
lectern/contrib/yaml_to_json.py
lectern/directive.py
lectern/document.py
lectern/extract.py
lectern/fragment.py
lectern/loaders.py
lectern/plugin.py
lectern/prefetch.py
lectern/py.typed
lectern/pytest_plugin.py
lectern/serialize.py
lectern-0.35.0.dist-info/licenses/LICENSE
lectern-0.35.0.dist-info/WHEEL
lectern-0.35.0.dist-info/entry_points.txt
lectern-0.35.0.dist-info/METADATA
lectern-0.35.0.dist-info/RECORD
