Metadata-Version: 2.4
Name: lectern
Version: 0.35.0
Summary: Literate Minecraft data packs and resource packs
Keywords: literate-programming,beet,resourcepack,minecraft,datapack
Author: Valentin Berlier
Author-email: Valentin Berlier <berlier.v@gmail.com>
License-Expression: MIT
License-File: LICENSE
Requires-Dist: beet>=0.113.0
Requires-Dist: markdown-it-py>=4.0.0
Requires-Python: >=3.14
Project-URL: Repository, https://github.com/mcbeet/beet/blob/main/packages/lectern
